maskingPackage/__init__.py
maskingPackage/encryption_logic.py
maskingPackage/encryptordecryptor.py
maskingPackage/maskingColumn.py
maskingPackage/masking_utils.py
maskingPackage-1.0.26.dist-info/METADATA
maskingPackage-1.0.26.dist-info/WHEEL
maskingPackage-1.0.26.dist-info/top_level.txt
maskingPackage-1.0.26.dist-info/RECORD
