Metadata-Version: 2.1
Name: maskingPackage
Version: 1.0.26
Requires-Dist: pandas
Requires-Dist: cryptography
